README
setup.cfg
setup.py
exgrexPytest/__init__.py
exgrexPytest/decorators.py
exgrexPytest/plugin.py
exgrex_pytest.egg-info/PKG-INFO
exgrex_pytest.egg-info/SOURCES.txt
exgrex_pytest.egg-info/dependency_links.txt
exgrex_pytest.egg-info/entry_points.txt
exgrex_pytest.egg-info/requires.txt
exgrex_pytest.egg-info/top_level.txt