Metadata-Version: 2.1
Name: exgrex-pytest
Version: 0.1a2
Summary: Package exgrex-pytest adds to package exgrex-py the ability to use the pytest framework.
Home-page: https://github.com/vshagur/exgrex-pytest
Author: vshagur
Author-email: vshagur@gmail.com
License: UNKNOWN
Keywords: mooc,grader,python,python3,education,exgrex,coursera,pytest
Platform: UNKNOWN
Classifier: Programming Language :: Python :: 3
Classifier: License :: OSI Approved :: MIT License
Classifier: Operating System :: POSIX :: Linux
Requires-Python: >=3.6
